[
  {
    "version": "V3.0",
    "date": "2026-06-13",
    "color": "#c9a050",
    "subtitle": "架构 V3 升级 · 数据校验管线 · 3D 星图 · 项目文档化",
    "items": [
      "<strong>数据校验管线</strong>：新增 `src/validators/validate-data.js`——JSON schema 校验 + crossRef 存在性检查 + eventId 全局唯一性检查 + 扁平化 + `event-index.json` 生成",
      "<strong>数据访问层</strong>：新增 `data-loader.js`（fetch + Map 缓存）+ `data-access.js`（4 个 async 函数，UI 永不直接访问数据结构）",
      "<strong>3D 星图首页</strong>：新增 `star-map-3d.js`——Three.js 银河场景，OrbitControls 漫游，~165K 粒子，HTML marker 投影 3D→2D",
      "<strong>动画 Token 系统</strong>：新增 `anim-tokens.js`——统一管理 duration/easing 常量",
      "<strong>项目文档化</strong>：新增 `docs/` 目录（ARCHITECTURE.md / GUIDELINES.md / PRD.md）",
      "<strong>日志规范</strong>：开发日志和更新日志移入 `docs/`，变更日志转换脚本适配新路径",
      "<strong>清理</strong>：移除 `materials/` 原始素材目录、`LICENSE` 文件",
      "<strong>修复</strong>：修复 `.gitignore` 未覆盖日志文件的问题，修复 `convert-changelog.js` 路径引用"
    ]
  },
  {
    "version": "V1.2",
    "date": "2026-06-13",
    "color": "#b8c4d8",
    "subtitle": "新增最终幻想XIV编年史 · 碎片世界分支架构",
    "items": [
      "新增<strong>最终幻想XIV</strong>编年史（艾欧泽亚 · 原初世界主线 + 第一世界 / 第十三世界碎片分支）",
      "星图首页新增第三星系——<strong>艾欧泽亚</strong>（四臂螺旋 · 以太银白主题）",
      "碎片世界采用方案 E 架构：原初主线 + 碎片分组标签页 + crossRefs 跨世界引用",
      "新增<strong>更新日志</strong>独立页面",
      "导航栏与页脚同步更新"
    ]
  },
  {
    "version": "V1.1",
    "date": "2026-06-13",
    "color": "#c85050",
    "subtitle": "多页重构 · 战锤40K上线",
    "items": [
      "SPA → <strong>多页静态网站</strong>重构（11ty + Nunjucks + esbuild）",
      "新增<strong>战锤40K</strong>编年史（帝国历 · 银河全史）",
      "星图首页、传送门过渡、虫洞导航上线",
      "虚拟滚动引擎、背景预设系统上线",
      "GitHub Pages 自动部署"
    ]
  },
  {
    "version": "V1.0",
    "date": "2026-06-12",
    "color": "#d4923a",
    "subtitle": "明日方舟编年史上线",
    "items": [
      "粒子星空背景（DSP 冷色银河风格）",
      "<strong>明日方舟</strong>编年史时间线上线（102 事件 / 14 时代 / 7 世界线）",
      "虚拟滚动、分支标签页、时代导航、事件卡片 3D 倾斜",
      "背景系统插件化（BG_PRESETS + ParticleBackground + BackgroundManager）"
    ]
  }
]
